[
    {
        "query": "What character did Christopher Lloyd portray in the Star Trek franchise?",
        "answer": "Commander Kruge",
        "level": "2",
        "type": "simple question",
        "subject": "Christopher Lloyd"
    },
    {
        "query": "Which character did Christopher Lloyd play in 'Who Framed Roger Rabbit'?",
        "answer": "Judge Doom",
        "level": "2",
        "type": "simple question",
        "subject": "Christopher Lloyd"
    },
    {
        "query": "What character did Christopher Lloyd play in 'Who Framed Roger Rabbit'?",
        "answer": "Judge Doom",
        "level": "2",
        "type": "simple question",
        "subject": "Christopher Lloyd"
    },
    {
        "query": "For which television series did Christopher Lloyd win his Emmy Awards?",
        "answer": "Taxi",
        "level": "2",
        "type": "simple question",
        "subject": "Christopher Lloyd"
    },
    {
        "query": "What role did Christopher Lloyd play in 'Who Framed Roger Rabbit'?",
        "answer": "Judge Doom",
        "level": "2",
        "type": "simple question",
        "subject": "Christopher Lloyd"
    },
    {
        "query": "Which character did Christopher Lloyd portray in the 'Taxi' TV series?",
        "answer": "Jim Ignatowski",
        "level": "2",
        "type": "simple question",
        "subject": "Christopher Lloyd"
    },
    {
        "query": "In which film did Christopher Lloyd play the character Judge Doom?",
        "answer": "Who Framed Roger Rabbit",
        "level": "2",
        "type": "simple question",
        "subject": "Christopher Lloyd"
    },
    {
        "query": "Which character did Christopher Lloyd portray in the film 'Clue'?",
        "answer": "Professor Plum",
        "level": "2",
        "type": "simple question",
        "subject": "Christopher Lloyd"
    },
    {
        "query": "What year was Christopher Lloyd born?",
        "answer": "1938",
        "level": "2",
        "type": "simple question",
        "subject": "Christopher Lloyd"
    },
    {
        "query": "In which animated film did Christopher Lloyd voice the character Grigori Rasputin?",
        "answer": "Anastasia",
        "level": "2",
        "type": "simple question",
        "subject": "Christopher Lloyd"
    },
    {
        "query": "Which role earned Lloyd two Primetime Emmy Awards while working on 'Taxi'?",
        "answer": "Jim Ignatowski",
        "level": "2",
        "type": "simple question",
        "subject": "Christopher Lloyd"
    },
    {
        "query": "What iconic trilogy is Christopher Lloyd known for?",
        "answer": "Back to the Future",
        "level": "2",
        "type": "simple question",
        "subject": "Christopher Lloyd"
    },
    {
        "query": "For which television sitcom did Christopher Lloyd win two Primetime Emmy Awards?",
        "answer": "Taxi",
        "level": "2",
        "type": "simple question",
        "subject": "Christopher Lloyd"
    }
]