[
    {
        "query": "What position did Alexander Hamilton first hold in the U.S. government?",
        "answer": "Secretary of the Treasury",
        "level": "2",
        "type": "simple question",
        "subject": "Alexander Hamilton"
    },
    {
        "query": "In which war did Alexander Hamilton serve as an artillery officer?",
        "answer": "American Revolutionary War",
        "level": "2",
        "type": "simple question",
        "subject": "Alexander Hamilton"
    },
    {
        "query": "Which convention did Hamilton lead to discuss replacing the Articles of Confederation?",
        "answer": "Annapolis Convention",
        "level": "2",
        "type": "simple question",
        "subject": "Alexander Hamilton"
    },
    {
        "query": "Which convention did Alexander Hamilton lead that aimed to replace the Articles of Confederation?",
        "answer": "Annapolis Convention",
        "level": "2",
        "type": "simple question",
        "subject": "Alexander Hamilton"
    },
    {
        "query": "Which convention did Hamilton lead in 1786?",
        "answer": "Annapolis Convention",
        "level": "2",
        "type": "simple question",
        "subject": "Alexander Hamilton"
    },
    {
        "query": "Where did Alexander Hamilton pursue his education?",
        "answer": "New York City",
        "level": "2",
        "type": "simple question",
        "subject": "Alexander Hamilton"
    },
    {
        "query": "Which party was founded on the basis of Hamilton's views?",
        "answer": "Federalist Party",
        "level": "2",
        "type": "simple question",
        "subject": "Alexander Hamilton"
    },
    {
        "query": "What role did Alexander Hamilton serve in George Washington's cabinet?",
        "answer": "Secretary of the Treasury",
        "level": "2",
        "type": "simple question",
        "subject": "Alexander Hamilton"
    },
    {
        "query": "Which treaty did Alexander Hamilton support to resume trade relations with the British Empire?",
        "answer": "Jay Treaty",
        "level": "2",
        "type": "simple question",
        "subject": "Alexander Hamilton"
    },
    {
        "query": "Which party was founded on the views of Alexander Hamilton?",
        "answer": "Federalist Party",
        "level": "2",
        "type": "simple question",
        "subject": "Alexander Hamilton"
    },
    {
        "query": "What island was Alexander Hamilton born on?",
        "answer": "Nevis",
        "level": "2",
        "type": "simple question",
        "subject": "Alexander Hamilton"
    },
    {
        "query": "Which college did Alexander Hamilton attend in New York City?",
        "answer": "King's College",
        "level": "2",
        "type": "simple question",
        "subject": "Alexander Hamilton"
    },
    {
        "query": "Which clergyman's pamphlets did Hamilton respond to with his first published political writings?",
        "answer": "Samuel Seabury",
        "level": "2",
        "type": "simple question",
        "subject": "Alexander Hamilton"
    },
    {
        "query": "In what year did Alexander Hamilton arrive in the North American colonies?",
        "answer": "1772",
        "level": "2",
        "type": "simple question",
        "subject": "Alexander Hamilton"
    },
    {
        "query": "Which college did Alexander Hamilton attend?",
        "answer": "King's College",
        "level": "2",
        "type": "simple question",
        "subject": "Alexander Hamilton"
    }
]